yeastmlp/__init__.py
yeastmlp/adhesion.py
yeastmlp/flocculation.py
yeastmlp-1.0.3.dist-info/LICENSE
yeastmlp-1.0.3.dist-info/METADATA
yeastmlp-1.0.3.dist-info/WHEEL
yeastmlp-1.0.3.dist-info/top_level.txt
yeastmlp-1.0.3.dist-info/RECORD
