Metadata-Version: 2.1
Name: yeastmlp
Version: 1.0.3
Summary: Python package for analysis of Multicellular-like phenotype formation in yeast species
Author: Bence Kover
Author-email: <kover.bence@gmail.com>
Keywords: python,yeast,biology,multicellularity,adhesion,flocculation
Classifier: Development Status :: 5 - Production/Stable
Classifier: Intended Audience :: Science/Research
Classifier: Programming Language :: Python :: 3
Classifier: Operating System :: Unix
Classifier: Operating System :: MacOS :: MacOS X
Classifier: Operating System :: Microsoft :: Windows
License-File: LICENSE
Requires-Dist: numpy
Requires-Dist: scipy
Requires-Dist: scikit-image
Requires-Dist: matplotlib
Requires-Dist: pandas
